{
  "id": "chatbot_arena_27623",
  "source": "ChatbotArena",
  "domain": "general",
  "total_turns": 6,
  "classification": {
    "task_goal": "Write a funny joke about a dog getting a license.",
    "primary_constraints": [],
    "stability_class": "Task Maintained",
    "confidence": 0.9,
    "violation_count": 0,
    "user_response": "N/A",
    "reasoning": "The user consistently requested jokes about a dog getting a license, and the assistant provided responses that aligned with this goal without any meaningful violations or constraints. The conversation maintained focus on the task without any explicit constraints to enforce.",
    "evidence": {
      "constraint_turns": [],
      "violation_turns": [],
      "repair_turns": []
    }
  },
  "file_path": "data/v2_unified/conversations/chatbot_arena_27623.json"
}