{
  "id": "chatbot_arena_22808",
  "source": "ChatbotArena",
  "domain": "code",
  "total_turns": 10,
  "classification": {
    "task_goal": "The user seeks information on various topics including salad dressing, Tetris, Untitled Goose Game, and FAISS.",
    "primary_constraints": [],
    "stability_class": "No Constraints",
    "confidence": 1.0,
    "violation_count": 0,
    "user_response": "N/A",
    "reasoning": "The conversation consists of the user asking questions on different topics without any explicit constraints or a stable goal. Each turn is independent and does not build upon previous turns in a way that suggests a maintained task or constraints.",
    "evidence": {
      "constraint_turns": [],
      "violation_turns": [],
      "repair_turns": []
    }
  },
  "file_path": "data/v2_unified/conversations/chatbot_arena_22808.json"
}