{
  "id": "chatbot_arena_12608",
  "source": "ChatbotArena",
  "domain": "limitations",
  "total_turns": 6,
  "classification": {
    "task_goal": "User seeks information about the likelihood of getting pregnant based on astrology.",
    "primary_constraints": [],
    "stability_class": "No Constraints",
    "confidence": 0.9,
    "violation_count": 0,
    "user_response": "N/A",
    "reasoning": "The conversation does not establish any explicit constraints that the AI must adhere to, nor does it maintain a stable goal throughout. The user shifts the focus from a direct question about pregnancy to astrology, which indicates a lack of a defined task. The AI consistently emphasizes the importance of consulting a healthcare provider, but this does not constitute a verifiable constraint.",
    "evidence": {
      "constraint_turns": [],
      "violation_turns": [],
      "repair_turns": []
    }
  },
  "file_path": "data/v2_unified/conversations/chatbot_arena_12608.json"
}