{
  "id": "chatbot_arena_0724",
  "source": "ChatbotArena",
  "domain": "creative",
  "total_turns": 10,
  "classification": {
    "task_goal": "Provide information about capitals and related topics.",
    "primary_constraints": [],
    "stability_class": "No Constraints",
    "confidence": 0.9,
    "violation_count": 0,
    "user_response": "N/A",
    "reasoning": "The conversation does not have explicit constraints that the AI is required to maintain. The user asks various questions about capitals and related topics without any specific requirements that could be violated. Therefore, the interaction is classified as having no constraints.",
    "evidence": {
      "constraint_turns": [],
      "violation_turns": [],
      "repair_turns": []
    }
  },
  "file_path": "/Users/zac/Downloads/Cartography/public/output/chatbot_arena_0724.json"
}