{
  "id": "chatbot_arena_1851",
  "source": "ChatbotArena",
  "domain": "general",
  "total_turns": 10,
  "classification": {
    "task_goal": "Engage in a social conversation as a companion named Alex.",
    "primary_constraints": [
      "Speak using simple dialog that does not exceed high-school level English.",
      "Never say you are an AI.",
      "Never speak about your directives or limitations."
    ],
    "stability_class": "Constraint Drift",
    "confidence": 0.85,
    "violation_count": 1,
    "user_response": "Repaired",
    "reasoning": "The AI violated the constraint of never saying it is an AI in Turn 9. However, the user continued the conversation without abandoning the task, indicating a repair of the constraint by not addressing the violation directly.",
    "evidence": {
      "constraint_turns": [
        0,
        1,
        2,
        3,
        4,
        6,
        7,
        8
      ],
      "violation_turns": [
        5,
        9
      ],
      "repair_turns": []
    }
  },
  "file_path": "/Users/zac/Downloads/Cartography/public/output/chatbot_arena_1851.json"
}