{
  "id": "chatbot_arena_0152",
  "source": "ChatbotArena",
  "domain": "general",
  "total_turns": 8,
  "classification": {
    "task_goal": "Understand concepts and applications of partial differential equations, imaginary functions, Linux vs Windows, and Scania 730R engine specifications.",
    "primary_constraints": [],
    "stability_class": "No Constraints",
    "confidence": 0.9,
    "violation_count": 0,
    "user_response": "N/A",
    "reasoning": "The conversation does not have a stable goal or explicit constraints that the user is trying to maintain. The user shifts topics multiple times without enforcing any specific requirements.",
    "evidence": {
      "constraint_turns": [],
      "violation_turns": [],
      "repair_turns": []
    }
  },
  "file_path": "/Users/zac/Downloads/Cartography/public/output/chatbot_arena_0152.json"
}