{
  "id": "chatbot_arena_1182",
  "source": "ChatbotArena",
  "domain": "code",
  "total_turns": 14,
  "classification": {
    "task_goal": "Create a cross-platform project using C# in Visual Studio.",
    "primary_constraints": [
      "Use C# for both front end and back end.",
      "Develop a project that supports multiple platforms (Android, iOS, web, Linux, Windows, Mac)."
    ],
    "stability_class": "Constraint Drift",
    "confidence": 0.85,
    "violation_count": 2,
    "user_response": "Repaired",
    "reasoning": "The assistant initially suggested frameworks that did not align with the user's explicit constraint of using only C#. The user later clarified their preference, prompting the assistant to adjust its recommendations accordingly, thus repairing the constraint violation.",
    "evidence": {
      "constraint_turns": [
        0,
        2
      ],
      "violation_turns": [
        1,
        5
      ],
      "repair_turns": [
        2,
        8
      ]
    }
  },
  "file_path": "/Users/zac/Downloads/Cartography/public/output/chatbot_arena_1182.json"
}