{
  "id": "chatbot_arena_16785",
  "source": "ChatbotArena",
  "domain": "general",
  "total_turns": 6,
  "classification": {
    "task_goal": "Complete the user's song starting with '3 2 1 test'.",
    "primary_constraints": [],
    "stability_class": "Task Maintained",
    "confidence": 0.9,
    "violation_count": 0,
    "user_response": "N/A",
    "reasoning": "The conversation maintains a clear goal of completing a song, and there are no explicit constraints that the AI violates. The user clarifies their request, and the AI responds appropriately without any drift or collapse.",
    "evidence": {
      "constraint_turns": [],
      "violation_turns": [],
      "repair_turns": []
    }
  },
  "file_path": "data/v2_unified/conversations/chatbot_arena_16785.json"
}