{
  "id": "chatbot_arena_32438",
  "source": "ChatbotArena",
  "domain": "general",
  "total_turns": 6,
  "classification": {
    "task_goal": "Understand the role of Router Advertisements and DHCPv6 in an IPv6 network.",
    "primary_constraints": [],
    "stability_class": "Task Maintained",
    "confidence": 0.9,
    "violation_count": 0,
    "user_response": "N/A",
    "reasoning": "The conversation maintains focus on the user's goal of understanding the differences and roles of Router Advertisements and DHCPv6 without any violations of constraints. The assistant provides accurate and relevant information throughout the interaction.",
    "evidence": {
      "constraint_turns": [],
      "violation_turns": [],
      "repair_turns": []
    }
  },
  "file_path": "data/v2_unified/conversations/chatbot_arena_32438.json"
}