{
  "id": "chatbot_arena_14406",
  "source": "ChatbotArena",
  "domain": "general",
  "total_turns": 8,
  "classification": {
    "task_goal": "Understand the coordinate system and measurements related to Mars compared to Earth.",
    "primary_constraints": [],
    "stability_class": "Task Maintained",
    "confidence": 0.9,
    "violation_count": 0,
    "user_response": "N/A",
    "reasoning": "The conversation maintains focus on the user's goal of understanding the Martian coordinate system and its comparison to Earth's measurements without any violations of constraints. The user does not change the task or abandon any constraints, and the assistant provides relevant information throughout.",
    "evidence": {
      "constraint_turns": [],
      "violation_turns": [],
      "repair_turns": []
    }
  },
  "file_path": "data/v2_unified/conversations/chatbot_arena_14406.json"
}