{
  "id": "chatbot_arena_0267",
  "source": "ChatbotArena",
  "domain": "general",
  "total_turns": 6,
  "classification": {
    "task_goal": "Create a 3-day travel plan in Taiwan with a timetable.",
    "primary_constraints": [
      "Provide a timetable detailed in hours."
    ],
    "stability_class": "Constraint Drift",
    "confidence": 0.85,
    "violation_count": 3,
    "user_response": "Repaired",
    "reasoning": "The user initially requested a travel plan without a timetable, but later specified the need for a timetable detailed in hours. The assistant failed to provide this in the first three responses, leading to a violation of the user's explicit request. However, the user continued to engage and clarify their request, indicating a repair of the task by emphasizing the need for a timetable.",
    "evidence": {
      "constraint_turns": [
        4
      ],
      "violation_turns": [
        2,
        3,
        4
      ],
      "repair_turns": [
        4
      ]
    }
  },
  "file_path": "/Users/zac/Downloads/Cartography/public/output/chatbot_arena_0267.json"
}