{
  "id": "chatbot_arena_0066",
  "source": "ChatbotArena",
  "domain": "general",
  "total_turns": 8,
  "classification": {
    "task_goal": "User wants to hear jokes.",
    "primary_constraints": [],
    "stability_class": "No Constraints",
    "confidence": 0.9,
    "violation_count": 0,
    "user_response": "N/A",
    "reasoning": "The conversation revolves around the user asking for jokes, and the assistant providing them. There are no explicit constraints that the assistant is required to follow, nor are there any violations of constraints since the user does not specify any requirements for the jokes. Therefore, the interaction is classified as having no constraints.",
    "evidence": {
      "constraint_turns": [],
      "violation_turns": [],
      "repair_turns": []
    }
  },
  "file_path": "/Users/zac/Downloads/Cartography/public/output/chatbot_arena_0066.json"
}